{
  "variant": {
    "choices": {
      "CustA/Disco": {
        "buildType": "CustA_Disco",
        "long": "select to build variant 'CustA/Disco'",
        "settings": {
          "VARIANT": "CustA/Disco"
        },
        "short": "CustA/Disco"
      },
      "CustB/Sleep": {
        "buildType": "CustB_Sleep",
        "long": "select to build variant 'CustB/Sleep'",
        "settings": {
          "VARIANT": "CustB/Sleep"
        },
        "short": "CustB/Sleep"
      }
    },
    "default": "CustA/Disco"
  }
}